main.py
setup.py
E3PO.egg-info/PKG-INFO
E3PO.egg-info/SOURCES.txt
E3PO.egg-info/dependency_links.txt
E3PO.egg-info/requires.txt
E3PO.egg-info/top_level.txt